wecon_greenlet/CObjects.cpp
wecon_greenlet/PyGreenlet.cpp
wecon_greenlet/PyGreenlet.hpp
wecon_greenlet/PyGreenletUnswitchable.cpp
wecon_greenlet/PyModule.cpp
wecon_greenlet/TBrokenGreenlet.cpp
wecon_greenlet/TExceptionState.cpp
wecon_greenlet/TGreenlet.cpp
wecon_greenlet/TGreenlet.hpp
wecon_greenlet/TGreenletGlobals.cpp
wecon_greenlet/TMainGreenlet.cpp
wecon_greenlet/TPythonState.cpp
wecon_greenlet/TStackState.cpp
wecon_greenlet/TThreadState.hpp
wecon_greenlet/TThreadStateCreator.hpp
wecon_greenlet/TThreadStateDestroy.cpp
wecon_greenlet/TUserGreenlet.cpp
wecon_greenlet/__init__.py
wecon_greenlet/__init__.pyc
wecon_greenlet/_greenlet.cpython-313t-arm-linux-gnueabihf.so
wecon_greenlet/greenlet.cpp
wecon_greenlet/greenlet.h
wecon_greenlet/greenlet_allocator.hpp
wecon_greenlet/greenlet_compiler_compat.hpp
wecon_greenlet/greenlet_cpython_compat.hpp
wecon_greenlet/greenlet_exceptions.hpp
wecon_greenlet/greenlet_internal.hpp
wecon_greenlet/greenlet_msvc_compat.hpp
wecon_greenlet/greenlet_refs.hpp
wecon_greenlet/greenlet_slp_switch.hpp
wecon_greenlet/greenlet_thread_support.hpp
wecon_greenlet/slp_platformselect.h
wecon_greenlet/__pycache__/__init__.cpython-313.pyc
wecon_greenlet/platform/__init__.py
wecon_greenlet/platform/__init__.pyc
wecon_greenlet/platform/setup_switch_x64_masm.cmd
wecon_greenlet/platform/switch_aarch64_gcc.h
wecon_greenlet/platform/switch_alpha_unix.h
wecon_greenlet/platform/switch_amd64_unix.h
wecon_greenlet/platform/switch_arm32_gcc.h
wecon_greenlet/platform/switch_arm32_ios.h
wecon_greenlet/platform/switch_arm64_masm.asm
wecon_greenlet/platform/switch_arm64_masm.obj
wecon_greenlet/platform/switch_arm64_msvc.h
wecon_greenlet/platform/switch_csky_gcc.h
wecon_greenlet/platform/switch_loongarch64_linux.h
wecon_greenlet/platform/switch_m68k_gcc.h
wecon_greenlet/platform/switch_mips_unix.h
wecon_greenlet/platform/switch_ppc64_aix.h
wecon_greenlet/platform/switch_ppc64_linux.h
wecon_greenlet/platform/switch_ppc_aix.h
wecon_greenlet-3.2.3.dist-info/METADATA
wecon_greenlet-3.2.3.dist-info/WHEEL
wecon_greenlet-3.2.3.dist-info/top_level.txt
wecon_greenlet-3.2.3.dist-info/RECORD
