Metadata-Version: 2.1
Name: wecon_greenlet
Version: 3.2.3
Summary: Auto-generated package for wecon_greenlet
Home-page: UNKNOWN
Author: WECON_HJB
License: UNKNOWN
Platform: linux-armv7l
Requires-Python: >=3.9
